sphinxcontrib_mscgenjs-0.1.4-py3.6-nspkg.pth
sphinxcontrib/mscgenjs/__init__.py
sphinxcontrib/mscgenjs/_static/mscgen-inpage.js
sphinxcontrib_mscgenjs-0.1.4.dist-info/LICENSE
sphinxcontrib_mscgenjs-0.1.4.dist-info/METADATA
sphinxcontrib_mscgenjs-0.1.4.dist-info/WHEEL
sphinxcontrib_mscgenjs-0.1.4.dist-info/namespace_packages.txt
sphinxcontrib_mscgenjs-0.1.4.dist-info/top_level.txt
sphinxcontrib_mscgenjs-0.1.4.dist-info/RECORD
