Metadata-Version: 2.1
Name: sphinxcontrib-mscgenjs
Version: 0.1.4
Summary: mscgenjs Sphinx extension
Home-page: https://github.com/LoveIsGrief/sphinxcontrib-mscgenjs
Author: LoveIsGrief
Author-email: loveisgrief@tuta.io
License: BOLA
Download-URL: http://pypi.python.org/pypi/sphinxcontrib-mscgenjs
Project-URL: Bugs, https://github.com/LoveIsGrief/sphinxcontrib-mscgenjs/issues
Platform: any
Classifier: Development Status :: 3 - Alpha
Classifier: Environment :: Console
Classifier: Environment :: Web Environment
Classifier: Intended Audience :: Developers
Classifier: License :: Public Domain
Classifier: Operating System :: OS Independent
Classifier: Programming Language :: Python
Classifier: Topic :: Documentation
Classifier: Topic :: Utilities
Requires-Dist: Sphinx (>=0.6)
